dbsod/__init__.py
dbsod/dbsod.cpp.so
dbsod/dbsod.py
dbsod-0.0.4.dist-info/licenses/LICENSE
dbsod-0.0.4.dist-info/METADATA
dbsod-0.0.4.dist-info/WHEEL
dbsod-0.0.4.dist-info/top_level.txt
dbsod-0.0.4.dist-info/RECORD
